<?xml version="1.0" encoding="UTF-8" standalone="yes"?>
<contentHaul xmlns:a="http://www.appian.com/ae/types/2009">
    <rule>
        <name>SCY_usermanage_interface</name>
        <uuid>_a-0000dbd2-16ce-8000-9ba2-011c48011c48_63499</uuid>
        <description></description>
        <parentUuid>_a-0000dbd2-16ce-8000-9ba2-011c48011c48_62739</parentUuid>
        <visibility>
            <advertise>false</advertise>
            <hierarchy>true</hierarchy>
            <indexable>true</indexable>
            <quota>false</quota>
            <searchable>true</searchable>
            <system>false</system>
            <unlogged>false</unlogged>
        </visibility>
        <definition>=#&quot;SYSTEM_SYSRULES_formLayout&quot;(
  label: &quot;Lorem Ipsum&quot;,
  instructions: &quot;Lorem Ipsum&quot;,
  firstColumnContents: {
    #&quot;SYSTEM_SYSRULES_gridField&quot;(
      label: &quot;user&quot;,
      labelPosition: &quot;ABOVE&quot;,
      totalCount: 0,
      columns: {
        #&quot;SYSTEM_SYSRULES_gridTextColumn&quot;(
          label: &quot;Column Label&quot;,
          data: {}
        )
      },
      value: #&quot;SYSTEM_SYSRULES_pagingInfo&quot;(startIndex: 1, batchSize: 5),
      saveInto: {},
      validations: {}
    )
  },
  secondColumnContents: {
    /* Add components here for a two-column form */
  },
  buttons: #&quot;SYSTEM_SYSRULES_ButtonLayout&quot;(
    primaryButtons: {
      #&quot;SYSTEM_SYSRULES_ButtonWidgetSubmit&quot;(
        label: &quot;Submit&quot;,
        style: &quot;PRIMARY&quot;,
        saveInto: {}
      )
    },
    secondaryButtons: {
      #&quot;SYSTEM_SYSRULES_ButtonWidgetSubmit&quot;(
        label: &quot;Cancel&quot;,
        style: &quot;NORMAL&quot;,
        value: true,
        saveInto: ri!cancel,
        skipValidation: true
      )
    }
  ),
  validations: {}
)</definition>
        <namedTypedValue>
            <name>cancel</name>
            <type>
                <name>boolean</name>
                <namespace>http://www.w3.org/2001/XMLSchema</namespace>
            </type>
        </namedTypedValue>
        <preferredEditor>interface</preferredEditor>
        <offlineEnabled>false</offlineEnabled>
    </rule>
    <roleMap public="true">
        <role allowForAll="false" inherit="true" name="readers">
            <users/>
            <groups/>
        </role>
        <role allowForAll="false" inherit="true" name="authors">
            <users/>
            <groups/>
        </role>
        <role allowForAll="false" inherit="true" name="administrators">
            <users/>
            <groups/>
        </role>
        <role allowForAll="false" inherit="false" name="denyReaders">
            <users/>
            <groups/>
        </role>
        <role allowForAll="false" inherit="false" name="denyAuthors">
            <users/>
            <groups/>
        </role>
        <role allowForAll="false" inherit="false" name="denyAdministrators">
            <users/>
            <groups/>
        </role>
    </roleMap>
    <typedValue>
        <type>
            <name>RuleTestConfig</name>
            <namespace>http://www.appian.com/ae/types/2009</namespace>
        </type>
        <value>
            <a:ruleInputTestConfigs>
                <a:value xmlns:xsi="http://www.w3.org/2001/XMLSchema-instance" xsi:nil="true" xsi:type="a:Expression"/>
                <a:nameRef>cancel</a:nameRef>
            </a:ruleInputTestConfigs>
        </value>
    </typedValue>
</contentHaul>
